sys_config/__init__.py
sys_config/main.py
sys_config-0.2.1.dist-info/LICENSE
sys_config-0.2.1.dist-info/WHEEL
sys_config-0.2.1.dist-info/METADATA
sys_config-0.2.1.dist-info/RECORD
