Metadata-Version: 2.1
Name: sys-config
Version: 0.2.1
Summary: Awesome `sys-config` is a Python cli/package created with https://github.com/william-cass-wright/cookiecutter-pypackage-slim
Home-page: https://github.com/sys_config/sys-config
License: GNU GPL v3.0
Author: sys-config
Author-email: hello@sys-config.com
Requires-Python: >=3.9,<4.0
Classifier: Development Status :: 3 - Alpha
Classifier: Intended Audience :: Developers
Classifier: License :: OSI Approved :: GNU General Public License v3 or later (GPLv3+)
Classifier: License :: Other/Proprietary License
Classifier: Operating System :: OS Independent
Classifier: Programming Language :: Python :: 3
Classifier: Programming Language :: Python :: 3.10
Classifier: Programming Language :: Python :: 3.9
Classifier: Topic :: Software Development :: Libraries :: Python Modules
Project-URL: Repository, https://github.com/sys_config/sys-config
